{
  "id": 137,
  "slug": "buyuk-kartalin-olumu-ve-sonrasi",
  "title": "Büyük Kartal’ın Ölümü ve Sonrası",
  "date": "2025-04-27T03:06:54Z",
  "modified": "2025-04-27T03:39:34Z",
  "author": {
    "id": 2,
    "name": "Süleyman Armağan Er",
    "slug": "armagan-er",
    "description": "",
    "avatar": "https://secure.gravatar.com/avatar/e618616356a63411357a78320e4c995dbe10eda6c620baec0d6e7a23919dea75?s=96&d=mm&r=g"
  },
  "categories": [
    {
      "id": 1,
      "name": "Uncategorized",
      "slug": "uncategorized"
    }
  ],
  "excerpt": "",
  "featuredImage": null,
  "featuredImageAlt": "",
  "content": "\n\n\n\n\n<blockquote class=\"wp-block-quote is-layout-flow wp-block-quote-is-layout-flow\">\n<p><em>Saltanat didükleri ancak cihân gavgasıdur</em></p>\n\n\n\n<p>(<em>Saltanat dedikleri sadece bir dünya kavgasıdır</em>)</p>\n\n\n\n<p><em>Olmaya baht u sa&#8217;âdet dünyede vahdet gibi</em></p>\n\n\n\n<p>(<em>Dünyada Allah’a yakınlık kadar büyük mutluluk ve baht açıklığı olamaz</em>)</p>\n</blockquote>\n\n\n\n<p>Kanuni Sultan Süleyman’ın Muhibbi mahlasıyla yazdığı divan şiirlerinden belki de en ünlüsü olan ve Halk içinde muteber bir nesne yok devlet gibi dizesiyle başlayan şiirden alıntı olan bu beyitin, saltanat için iki oğlunu ve onlardan olma birçok erkek torununu öldürtmüş bu ünlü Türk hükümdarın kaleminden çıkması anlamlıdır. Bütün Türk tarihinde olduğu gibi Osmanlı devleti tarihi de saltanat uğruna sayısız darbe, ihanet ve savaş ile doludur. Taht için Yavuz Sultan Selim’in babası II. Bayezid’i 1517’de alaşağı etmesi ve sonrasında muhtemelen zehirletmesi, III. Mehmed’in 1595’te tahta çıktığında tam 19 kardeşini boğdurtması, 1622’de Genç Osman’ın yeniçerilerin başını çektiği bir isyanla hakaretler edilerek gaddarca öldürülmesi, 1808’de III. Selim’in büyük bir eziyetle katledilmesi gibi birçok hadise vuku bulmuştur.</p>\n\n\n\n<p>Yaşarken birçok kez zehirlenme teşebbüslerinden kurtulan ve Memlük devleti üzerine yapılacak bir sefere hazırlanırken şüpheli bir şekilde 1481 yılında 51 yaşında vefat eden Fatih’in ölümü Hristiyan dünyasında büyük sevinç yaratmış, Venedikliler <strong>𝗟𝗮 𝗚𝗿𝗮𝗻𝗱𝗲 𝗔𝗾𝘂𝗶𝗹𝗮 𝗲̀ 𝗺𝗼𝗿𝘁𝗮! </strong>yani büyük kartal öldü [1] diyerek kilise çanları çalmış, kutlamalar yapmışlardır. Avrupa bu haberle çalkalanırken Fatih’in hayattaki iki oğlu Şehzade Bayezid ve Şehzade Cem arasındaki taht kavgası tüm hızıyla başlamıştır. Bu mücadele o kadar kontrolden çıkmıştır ki Hz. Muhammed’in müjdelediği İstanbul’un fethini gerçekleştirmiş büyük Türk hakanı Fatih’in naaşı ortada bırakılmıştır. Devlet erkanı iki şehzade arkasında ikiye bölünmüş, Sadrazam Karamani Mehmed Paşa’nın başını çektiği grup küçük oğul Cem’i desteklerken, deneyimli vezir İshak Paşa’nın başını çektiği grup büyük oğul Bayezid’i tahta çıkarmak istemiştir. Fatih’in sefer yolunda Gebze civarlarında Tekfur çayırı olarak bilinen yerde vefatı akabinde cenazesi gizlice Topkapı Sarayına getirilmiştir. Sultanın vefatının haberi 11 gün sonra ordugahta yayılmış, Yeniçeriler kayıklarla İstanbul’a geçerek Sadrazam Karamani Mehmed Paşa’yı öldürmüş ve şehri yağmalamışlardır. Topkapı Saray arşivinden bir belgeye göre Baltacılar Kethüdası Kasım Sultan II. Bayezid’e şunları söylemiştir:</p>\n\n\n\n<blockquote class=\"wp-block-quote is-layout-flow wp-block-quote-is-layout-flow\">\n<p><em>Ol halde hünkâr müteveffa oldu, üzerinde üç gün üç gece mum yanmadı. Vardım kapıcılar kethüdasına söyledim. Ol dahi ishak paşa’ya söyledi. Emreylediler, mum yaktım, rayihasından kimse yanına varamadı. Ben fakir usta ile bilece içini ayırtladım.</em></p>\n</blockquote>\n\n\n\n<p>Dolayısıyla, tüm bu olayların telaşında Fatih Sultan Mehmed’in naaşının tam üç gün boyunca unutulduğu anlaşılmaktadır. Mayıs ayının sıcağında ulu Fatih’in cesedi on günden uzun bir süre üstünde elbisesiyle ortada kaldığı için oluşan kokudan dolayı odaya kimse girememiş, Baltacılar Kethüdası ile bir usta Fatih’i gasletmiş ve Selçuklular ve beyliklerde de görülen eski Türk geleneklerine uygun olarak iç organlarını çıkartıp ve mumyalayıp kefenlemişlerdir. Sonuç olarak, Fatih Sultan Mehmed’in ölümü saltanat mücadelesinin insanları kendisine ne denli esir yaptığını bir kere daha göstermiştir. Bayezid, saltanatı ele geçirip sultan olmuş, kardeşine karşı savaşını kaybeden Cem kaçmıştır. Cem Sultan meselesi Osmanlı’yı Bayezid döneminde Avrupa siyasetinde zor duruma sokmuştur. Rodos Şövalyeleri ve daha sonrasında Papalık tarafından rehine olarak tutulan şehzade, Osmanlı’ya karşı Hristiyan dünyası tarafından uzun yıllar boyu bir baskı unsuru olarak kullanılmıştır. Rodos, Fransa ve İtalya’da oradan oraya sıkıntı ve ümitsizliklerle dolu bir hayat geçiren Cem’in şiirlerinde genç yaşta vatanından uzakta kalmanın etkisiyle gurbet teması önemli bir yerdedir ve bu yönüyle bize Divan edebiyatında nadir olan gurbet ve vatan şiirlerinin ilk örneklerini vermiştir [3].</p>\n\n\n\n<p>Bu yazıyı Farsça ve Türkçe iki divanı bulunan Cem Sultan’ın gurbetteki vatan hasretini anlatan bir şiiriyle bitirelim:</p>\n\n\n\n<blockquote class=\"wp-block-quote is-layout-flow wp-block-quote-is-layout-flow\">\n<p><em>Cân dimâğına ereli bûy-ı vatan</em></p>\n\n\n\n<p><em>Dil diler kim görüne rûy-ı vatan</em><br><br></p>\n\n\n\n<p><em>Çeşme-i hayvândan ey cân hoş durur</em></p>\n\n\n\n<p><em>Ben garîb üftâdeye cûy-ı vatan</em><br><br></p>\n\n\n\n<p><em>N’ola cândan istesem çün yeğ durur</em></p>\n\n\n\n<p><em>Bâğ-ı cennetten bana kûy-ı vatan</em><br><br></p>\n\n\n\n<p><em>Gönlüm eyler dâimâ onu taleb</em></p>\n\n\n\n<p><em>Bend olaldan bana gîsû-yı vatan</em><br><br></p>\n\n\n\n<p><em>Hurrem olup cân-ı Cem irdi safâ</em></p>\n\n\n\n<p><em>Dil sabâdan alalı bûy-ı vatan</em></p>\n\n\n\n<p><em>“Vatan kokusu can dimağına ulaştığında gönül, vatanın yüzünü görmek ister. Vatanın ırmakları gurbete düşmüş bana âb-ı hayattan daha hoş gelir. Çünkü vatanın bir köşesi bile bana cennet bahçelerinden daha iyi geldiği için vatanı gönülden arzulasam bunda şaşılacak bir şey yok. (Tıpkı bir güzelin gibi) vatanımın uzun siyah saçlarına bağlanalı gönlüm hep onu ister. Cem’in gönlü, sabah rüzgârının getirdiği vatan kokusunu aldığından beri mutludur, sevinçlidir [3].”</em></p>\n</blockquote>\n\n\n\n<p>Kaynakça</p>\n\n\n\n<p>[1] Dizionario Biografico degli Italiani, <a href=\"https://www.treccani.it/enciclopedia/battista-gritti_(Dizionario-Biografico)/\">https://www.treccani.it/enciclopedia/battista-gritti_(Dizionario-Biografico)/</a></p>\n\n\n\n<p>[2] Fatih Sultan Mehmed’in ölümü, İsmail Hakkı Uzunçarşılı</p>\n\n\n\n<p>[3] İki Gurbet Şâiri: Bâbür Şâh ve Cem Sultân’ın Şiirlerinde Vatan,Hanzade Güzeloğlu</p>\n\n\n"
}
